lionplot/__init__.py
lionplot/plot.py
lionplot-0.1.1.dist-info/LICENSE
lionplot-0.1.1.dist-info/METADATA
lionplot-0.1.1.dist-info/WHEEL
lionplot-0.1.1.dist-info/top_level.txt
lionplot-0.1.1.dist-info/RECORD
