Metadata-Version: 2.2
Name: lionplot
Version: 0.1.1
Summary: Package to create categorical scatterplots with error bars
Author-email: Leonardo Alchieri <leonard@alchieri.eu>
License: MIT
Project-URL: Homepage, https://github.com/LeonardoAlchieri/Lionplot
Project-URL: Issues, https://github.com/LeonardoAlchieri/Lionplot/issues
Classifier: Programming Language :: Python :: 3
Classifier: Operating System :: OS Independent
Classifier: Development Status :: 2 - Pre-Alpha
Classifier: License :: OSI Approved :: MIT License
Requires-Python: >=3.8
License-File: LICENSE
Requires-Dist: numpy
Requires-Dist: matplotlib
